pyzedis/__init__.py
pyzedis-0.0.1.dist-info/METADATA
pyzedis-0.0.1.dist-info/WHEEL
pyzedis-0.0.1.dist-info/top_level.txt
pyzedis-0.0.1.dist-info/RECORD
