Metadata-Version: 2.1
Name: pyzedis
Version: 0.0.1
Summary: A Python client for zedis
Home-page: https://github.com/drbh/pyzedis
Author: David Holtz
Author-email: david.richard.holtz@gmail.com
License: UNKNOWN
Platform: UNKNOWN
Classifier: Programming Language :: Python :: 3
Classifier: Operating System :: OS Independent
